[
  {
    "id": "cart_1756639509072_hhenz",
    "toyId": "toy_1756310935516_tgecf",
    "quantity": 5,
    "addedAt": "2025-08-31T11:25:09.072Z"
  },
  {
    "id": "cart_1756639510136_lphou",
    "toyId": "toy_1756311302843_ooaza",
    "quantity": 1,
    "addedAt": "2025-08-31T11:25:10.136Z"
  },
  {
    "id": "cart_1756639511730_6f9g5",
    "toyId": "toy_1756624721703_8nwm1",
    "quantity": 1,
    "addedAt": "2025-08-31T11:25:11.730Z"
  },
  {
    "id": "cart_1756639514386_6hbga",
    "toyId": "toy_1756311383109_n1347",
    "quantity": 1,
    "addedAt": "2025-08-31T11:25:14.386Z"
  },
  {
    "id": "cart_1756807429726_rsbw5",
    "toyId": "toy_1756747814679_el2b6",
    "quantity": 1,
    "addedAt": "2025-09-02T10:03:49.726Z"
  }
]